{
	"Id": "85",
	"Employees": [
		{
			"Id": "161",
			"Position": "55",
			"Head": false
		},
		{
			"Id": "192",
			"Position": "60",
			"Head": false
		},
		{
			"Id": "1061",
			"Position": "147",
			"Head": false
		},
		{
			"Id": "1516",
			"Position": "147",
			"Head": false
		},
		{
			"Id": "1556",
			"Position": "191",
			"Head": false
		},
		{
			"Id": "1795",
			"Position": "55",
			"Head": false
		},
		{
			"Id": "1848",
			"Position": "191",
			"Head": false
		},
		{
			"Id": "1880",
			"Position": "47",
			"Head": false
		},
		{
			"Id": "2247",
			"Position": "191",
			"Head": false
		},
		{
			"Id": "2439",
			"Position": "147",
			"Head": false
		},
		{
			"Id": "2617",
			"Position": "60",
			"Head": false
		},
		{
			"Id": "2635",
			"Position": "47",
			"Head": false
		},
		{
			"Id": "2817",
			"Position": "191",
			"Head": false
		},
		{
			"Id": "2878",
			"Position": "191",
			"Head": false
		},
		{
			"Id": "2943",
			"Position": "191",
			"Head": false
		},
		{
			"Id": "2945",
			"Position": "191",
			"Head": false
		},
		{
			"Id": "2953",
			"Position": "214",
			"Head": false
		},
		{
			"Id": "2957",
			"Position": "191",
			"Head": false
		},
		{
			"Id": "2988",
			"Position": "47",
			"Head": false
		},
		{
			"Id": "3023",
			"Position": "55",
			"Head": false
		},
		{
			"Id": "3128",
			"Position": "35",
			"Head": false
		},
		{
			"Id": "3287",
			"Position": "47",
			"Head": false
		},
		{
			"Id": "3456",
			"Position": "147",
			"Head": false
		},
		{
			"Id": "3461",
			"Position": "214",
			"Head": false
		},
		{
			"Id": "3704",
			"Position": "147",
			"Head": false
		},
		{
			"Id": "3746",
			"Position": "54",
			"Head": false
		}
	]
}
